summations/__init__.py
summations/summations.py
summations-0.0.9.1.dist-info/LICENSE
summations-0.0.9.1.dist-info/METADATA
summations-0.0.9.1.dist-info/WHEEL
summations-0.0.9.1.dist-info/top_level.txt
summations-0.0.9.1.dist-info/RECORD
