Metadata-Version: 2.1
Name: summations
Version: 0.0.9.1
Summary: Library to enumerate all natural number lists with a target sum.
Home-page: https://github.com/reity/summations-py
Author: Andrei Lapets
Author-email: a@lapets.io
License: MIT
Platform: UNKNOWN
